[
	{
		"__TYPE__": "SharedSliceContent",
		"variation": "default",
		"primary": {
			"id_key": {
				"__TYPE__": "FieldContent",
				"value": "class",
				"type": "Text"
			},
			"information_size": {
				"__TYPE__": "FieldContent",
				"value": "Small",
				"type": "Select"
			},
			"title_color": {
				"__TYPE__": "FieldContent",
				"value": "#7d9144",
				"type": "Color"
			},
			"subtitle_color": {
				"__TYPE__": "FieldContent",
				"value": "#3a198a",
				"type": "Color"
			},
			"text_background_color": {
				"__TYPE__": "FieldContent",
				"value": "#b90e42",
				"type": "Color"
			},
			"button_color": {
				"__TYPE__": "FieldContent",
				"value": "White",
				"type": "Select"
			},
			"title": {
				"__TYPE__": "FieldContent",
				"value": "sell",
				"type": "Text"
			},
			"subtitle": {
				"__TYPE__": "FieldContent",
				"value": "teeth",
				"type": "Text"
			},
			"description": {
				"__TYPE__": "StructuredTextContent",
				"value": [
					{
						"type": "paragraph",
						"content": {
							"text": "Eu proident amet anim laborum voluptate sint consequat aliqua esse sint ut ut. Elit laborum mollit cillum id sit esse eiusmod velit Lorem velit ea irure ut consectetur. Mollit magna nulla ut veniam id sit incididunt labore quis."
						}
					}
				]
			},
			"image": {
				"origin": {
					"id": "main",
					"url": "https://images.unsplash.com/photo-1547394765-185e1e68f34e",
					"width": 6000,
					"height": 4000
				},
				"url": "https://images.unsplash.com/photo-1547394765-185e1e68f34e",
				"width": 6000,
				"height": 4000,
				"edit": {
					"zoom": 1,
					"crop": {
						"x": 0,
						"y": 0
					},
					"background": "transparent"
				},
				"credits": null,
				"alt": null,
				"__TYPE__": "ImageContent",
				"thumbnails": {}
			},
			"button_label": {
				"__TYPE__": "FieldContent",
				"value": "walk",
				"type": "Text"
			},
			"link_button": {
				"__TYPE__": "BooleanContent",
				"value": false
			},
			"button_url": {
				"__TYPE__": "FieldContent",
				"value": "hair",
				"type": "Text"
			},
			"background_color": {
				"__TYPE__": "FieldContent",
				"value": "#ffffff",
				"type": "Color"
			},
			"image_position": {
				"__TYPE__": "FieldContent",
				"value": "right",
				"type": "Select"
			},
			"margin": {
				"__TYPE__": "FieldContent",
				"value": "jet",
				"type": "Text"
			},
			"grid_gap": {
				"__TYPE__": "FieldContent",
				"value": "basket",
				"type": "Text"
			},
			"description_color": {
				"__TYPE__": "FieldContent",
				"value": "#000000",
				"type": "Color"
			},
			"font_color": {
				"__TYPE__": "FieldContent",
				"value": "#b82d6b",
				"type": "Color"
			},
			"font_color_in_darkmode": {
				"__TYPE__": "FieldContent",
				"value": "#ceb6e1",
				"type": "Color"
			},
			"background_in_dark_mode": {
				"__TYPE__": "FieldContent",
				"value": "#4be53c",
				"type": "Color"
			},
			"fontFamily": {
				"__TYPE__": "FieldContent",
				"value": "Space Grotesk Variable",
				"type": "Select"
			},
			"custom_title_size": {
				"__TYPE__": "FieldContent",
				"value": "gave",
				"type": "Text"
			},
			"custom_subtitle_size": {
				"__TYPE__": "FieldContent",
				"value": "steady",
				"type": "Text"
			},
			"font_family_subtitle": {
				"__TYPE__": "FieldContent",
				"value": "Space Grotesk Variable",
				"type": "Select"
			},
			"students_avatars": {
				"__TYPE__": "StructuredTextContent",
				"value": [
					{
						"type": "paragraph",
						"content": {
							"text": "Consequat enim consequat quis consequat fugiat cupidatat veniam dolor irure ea ad."
						}
					}
				]
			},
			"student_avatar_description": {
				"__TYPE__": "FieldContent",
				"value": "rising",
				"type": "Text"
			},
			"description_title": {
				"__TYPE__": "FieldContent",
				"value": "children",
				"type": "Text"
			},
			"transparent": {
				"__TYPE__": "BooleanContent",
				"value": true
			},
			"button_label_size": {
				"__TYPE__": "FieldContent",
				"value": "actual",
				"type": "Text"
			},
			"description_font_size": {
				"__TYPE__": "FieldContent",
				"value": "success",
				"type": "Text"
			},
			"margin_top": {
				"__TYPE__": "FieldContent",
				"value": "pie",
				"type": "Text"
			},
			"margin_bottom": {
				"__TYPE__": "FieldContent",
				"value": "here",
				"type": "Text"
			},
			"max_width": {
				"__TYPE__": "FieldContent",
				"value": "we",
				"type": "Text"
			},
			"border_radius": {
				"__TYPE__": "FieldContent",
				"value": "onto",
				"type": "Text"
			}
		},
		"items": [
			{
				"__TYPE__": "GroupItemContent",
				"value": [
					[
						"multi_description_title",
						{
							"__TYPE__": "FieldContent",
							"value": "afternoon",
							"type": "Text"
						}
					],
					[
						"multi_description_content",
						{
							"__TYPE__": "FieldContent",
							"value": "snow",
							"type": "Text"
						}
					]
				]
			}
		]
	}
]