{
  "uid": {
    "__TYPE__": "UIDContent",
    "value": "little"
  },
  "title": {
    "__TYPE__": "FieldContent",
    "value": "example",
    "type": "Text"
  },
  "description": {
    "__TYPE__": "FieldContent",
    "value": "height",
    "type": "Text"
  },
  "image": {
    "__TYPE__": "ImageContent",
    "origin": {
      "id": "main",
      "url": "https://images.unsplash.com/photo-1607582278038-6bebbd4d7b72",
      "width": 4010,
      "height": 4010
    },
    "url": "https://images.unsplash.com/photo-1607582278038-6bebbd4d7b72",
    "width": 4010,
    "height": 4010,
    "edit": {
      "zoom": 1,
      "crop": {
        "x": 0,
        "y": 0
      },
      "background": "transparent"
    },
    "thumbnails": {}
  },
  "type": {
    "__TYPE__": "FieldContent",
    "value": "native",
    "type": "Text"
  },
  "slices": {
    "__TYPE__": "SliceContentType",
    "value": [
      {
        "key": "title_introduction$fb2ce5a9-3fca-47a2-9012-d53c1e6a2aab",
        "name": "title_introduction",
        "widget": {
          "__TYPE__": "SharedSliceContent",
          "variation": "default",
          "primary": {
            "title": {
              "__TYPE__": "StructuredTextContent",
              "value": [
                {
                  "type": "heading1",
                  "content": {
                    "text": "Factory"
                  }
                }
              ]
            },
            "buttontext": {
              "__TYPE__": "StructuredTextContent",
              "value": [
                {
                  "type": "paragraph",
                  "content": {
                    "text": "Quis ea amet commodo nostrud sint consequat consectetur ut. Velit qui elit elit aliqua qui amet anim laborum pariatur commodo eiusmod deserunt pariatur."
                  }
                }
              ]
            },
            "highlight": {
              "__TYPE__": "StructuredTextContent",
              "value": [
                {
                  "type": "paragraph",
                  "content": {
                    "text": "Nostrud culpa enim ut irure sunt est amet amet ex. Et adipisicing deserunt commodo non enim est reprehenderit sint. Ut esse consequat exercitation consectetur dolore."
                  }
                }
              ]
            },
            "description": {
              "__TYPE__": "StructuredTextContent",
              "value": [
                {
                  "type": "paragraph",
                  "content": {
                    "text": "Laboris labore exercitation officia. Exercitation ullamco exercitation ut."
                  }
                }
              ]
            },
            "bullets": {
              "__TYPE__": "StructuredTextContent",
              "value": [
                {
                  "type": "paragraph",
                  "content": {
                    "text": "Duis ullamco culpa laboris dolore deserunt. Deserunt occaecat ullamco ea ullamco culpa commodo tempor elit ipsum occaecat elit cupidatat enim duis. Nostrud proident sunt irure aliqua consequat tempor."
                  }
                }
              ]
            },
            "image": {
              "__TYPE__": "ImageContent",
              "origin": {
                "id": "main",
                "url": "https://images.unsplash.com/photo-1576662712957-9c79ae1280f8",
                "width": 3456,
                "height": 3456
              },
              "url": "https://images.unsplash.com/photo-1576662712957-9c79ae1280f8?rect=0%2C0%2C3456%2C3456&w=400&h=400",
              "width": 400,
              "height": 400,
              "edit": {
                "zoom": 1,
                "crop": {
                  "x": 0,
                  "y": 0
                },
                "background": "transparent"
              },
              "thumbnails": {}
            }
          },
          "items": [
            {
              "__TYPE__": "GroupItemContent",
              "value": []
            }
          ]
        }
      },
      {
        "key": "markdown$1523e032-f4ee-45b5-84b3-276accb200ff",
        "name": "markdown",
        "widget": {
          "__TYPE__": "SharedSliceContent",
          "variation": "default",
          "primary": {
            "title": {
              "__TYPE__": "FieldContent",
              "value": "eager",
              "type": "Text"
            },
            "description": {
              "__TYPE__": "FieldContent",
              "value": "hurt",
              "type": "Text"
            },
            "markdown": {
              "__TYPE__": "StructuredTextContent",
              "value": [
                {
                  "type": "paragraph",
                  "content": {
                    "text": "Dolor adipisicing excepteur cupidatat nulla do sint officia officia qui ex eu elit labore."
                  }
                }
              ]
            },
            "enable_table_of_content": {
              "__TYPE__": "BooleanContent",
              "value": false
            }
          },
          "items": [
            {
              "__TYPE__": "GroupItemContent",
              "value": []
            }
          ]
        }
      },
      {
        "key": "two_column$e2313626-acc9-4ae2-a3e7-b25f8da03926",
        "name": "two_column",
        "widget": {
          "__TYPE__": "SharedSliceContent",
          "variation": "default",
          "primary": {
            "title": {
              "__TYPE__": "FieldContent",
              "value": "highest",
              "type": "Text"
            },
            "subtitle": {
              "__TYPE__": "FieldContent",
              "value": "since",
              "type": "Text"
            },
            "description": {
              "__TYPE__": "StructuredTextContent",
              "value": [
                {
                  "type": "paragraph",
                  "content": {
                    "text": "Amet consectetur sint laborum sunt excepteur ut laboris."
                  }
                }
              ]
            },
            "image": {
              "__TYPE__": "ImageContent",
              "origin": {
                "id": "main",
                "url": "https://images.unsplash.com/photo-1589321578146-4c1ba445cc88",
                "width": 3168,
                "height": 4752
              },
              "url": "https://images.unsplash.com/photo-1589321578146-4c1ba445cc88",
              "width": 3168,
              "height": 4752,
              "edit": {
                "zoom": 1,
                "crop": {
                  "x": 0,
                  "y": 0
                },
                "background": "transparent"
              },
              "thumbnails": {}
            },
            "button_label": {
              "__TYPE__": "FieldContent",
              "value": "studying",
              "type": "Text"
            },
            "link_button": {
              "__TYPE__": "BooleanContent",
              "value": false
            },
            "button_url": {
              "__TYPE__": "LinkContent",
              "value": {
                "__TYPE__": "ExternalLink",
                "url": "https://prismic.io"
              }
            },
            "background_color": {
              "__TYPE__": "FieldContent",
              "value": "#66557b",
              "type": "Color"
            },
            "image_position": {
              "__TYPE__": "FieldContent",
              "value": "right",
              "type": "Select"
            }
          },
          "items": [
            {
              "__TYPE__": "GroupItemContent",
              "value": []
            }
          ]
        }
      },
      {
        "key": "one_column$c0b5ce4d-4db4-45f9-af84-17a756064162",
        "name": "one_column",
        "widget": {
          "__TYPE__": "SharedSliceContent",
          "variation": "default",
          "primary": {
            "title": {
              "__TYPE__": "FieldContent",
              "value": "distant",
              "type": "Text"
            },
            "subtitle": {
              "__TYPE__": "FieldContent",
              "value": "service",
              "type": "Text"
            },
            "description": {
              "__TYPE__": "StructuredTextContent",
              "value": [
                {
                  "type": "paragraph",
                  "content": {
                    "text": "Fugiat eu laborum nostrud commodo. Est est voluptate deserunt nisi ex magna ullamco non dolore proident adipisicing laborum officia. Minim duis culpa pariatur dolor eu reprehenderit laborum veniam tempor enim Lorem fugiat quis consequat."
                  }
                }
              ]
            },
            "button_label": {
              "__TYPE__": "FieldContent",
              "value": "pale",
              "type": "Text"
            },
            "link_button": {
              "__TYPE__": "BooleanContent",
              "value": false
            },
            "button_url": {
              "__TYPE__": "LinkContent",
              "value": {
                "__TYPE__": "ExternalLink",
                "url": "http://twitter.com"
              }
            },
            "kpi_title_1": {
              "__TYPE__": "FieldContent",
              "value": "three",
              "type": "Text"
            },
            "kpi_description_1": {
              "__TYPE__": "FieldContent",
              "value": "visitor",
              "type": "Text"
            },
            "kpi_color_1": {
              "__TYPE__": "FieldContent",
              "value": "#725035",
              "type": "Color"
            },
            "kpi_title_2": {
              "__TYPE__": "FieldContent",
              "value": "nodded",
              "type": "Text"
            },
            "kpi_description_2": {
              "__TYPE__": "FieldContent",
              "value": "couple",
              "type": "Text"
            },
            "kpi_color_2": {
              "__TYPE__": "FieldContent",
              "value": "#3b5bf5",
              "type": "Color"
            },
            "kpi_title_3": {
              "__TYPE__": "FieldContent",
              "value": "fort",
              "type": "Text"
            },
            "kpi_description_3": {
              "__TYPE__": "FieldContent",
              "value": "suit",
              "type": "Text"
            },
            "kpi_color_3": {
              "__TYPE__": "FieldContent",
              "value": "#e33295",
              "type": "Color"
            },
            "background": {
              "__TYPE__": "FieldContent",
              "value": "#c262e2",
              "type": "Color"
            }
          },
          "items": [
            {
              "__TYPE__": "GroupItemContent",
              "value": []
            }
          ]
        }
      },
      {
        "key": "testimonials$9faaf6d6-92e3-4eb3-a8a6-5698c2f19ed7",
        "name": "testimonials",
        "widget": {
          "__TYPE__": "SharedSliceContent",
          "variation": "default",
          "primary": {
            "title": {
              "__TYPE__": "FieldContent",
              "value": "bad",
              "type": "Text"
            },
            "endpoint": {
              "__TYPE__": "FieldContent",
              "value": "advice",
              "type": "Text"
            }
          },
          "items": [
            {
              "__TYPE__": "GroupItemContent",
              "value": []
            }
          ]
        }
      },
      {
        "key": "show_prices$eb970df4-cdf5-4081-9f6e-5cc1f07b2060",
        "name": "show_prices",
        "widget": {
          "__TYPE__": "SharedSliceContent",
          "variation": "default",
          "primary": {
            "title": {
              "__TYPE__": "FieldContent",
              "value": "opinion",
              "type": "Text"
            },
            "description": {
              "__TYPE__": "StructuredTextContent",
              "value": [
                {
                  "type": "paragraph",
                  "content": {
                    "text": "Magna adipisicing Lorem velit elit tempor velit."
                  }
                }
              ]
            },
            "plan": {
              "__TYPE__": "FieldContent",
              "value": "percent",
              "type": "Text"
            },
            "bullets": {
              "__TYPE__": "StructuredTextContent",
              "value": [
                {
                  "type": "paragraph",
                  "content": {
                    "text": "Officia elit non aute sit anim nostrud ullamco proident velit veniam do consectetur eiusmod aliquip. Nulla nisi elit voluptate. Do cupidatat nostrud ullamco excepteur cupidatat sunt."
                  }
                }
              ]
            }
          },
          "items": [
            {
              "__TYPE__": "GroupItemContent",
              "value": []
            }
          ]
        }
      },
      {
        "key": "technologies$35b6f84e-e3cc-4805-91b1-785342b9b68c",
        "name": "technologies",
        "widget": {
          "__TYPE__": "SharedSliceContent",
          "variation": "default",
          "primary": {
            "endpoint": {
              "__TYPE__": "FieldContent",
              "value": "either",
              "type": "Text"
            }
          },
          "items": [
            {
              "__TYPE__": "GroupItemContent",
              "value": []
            }
          ]
        }
      },
      {
        "key": "partners$aadba82c-35c0-4f71-bc4f-be4344601a47",
        "name": "partners",
        "widget": {
          "__TYPE__": "SharedSliceContent",
          "variation": "default",
          "primary": {
            "title": {
              "__TYPE__": "FieldContent",
              "value": "wave",
              "type": "Text"
            },
            "images": {
              "__TYPE__": "StructuredTextContent",
              "value": [
                {
                  "type": "paragraph",
                  "content": {
                    "text": "Fugiat aute amet consectetur laboris proident proident laborum cupidatat duis nulla ullamco velit. Elit laborum occaecat elit id nulla laborum ea ad magna ex dolor incididunt cillum nostrud."
                  }
                }
              ]
            }
          },
          "items": [
            {
              "__TYPE__": "GroupItemContent",
              "value": []
            }
          ]
        }
      },
      {
        "key": "road_map$0a9a5e22-7e53-40de-9447-05b11ac7643c",
        "name": "road_map",
        "widget": {
          "__TYPE__": "SharedSliceContent",
          "variation": "default",
          "primary": {
            "course_slug": {
              "__TYPE__": "FieldContent",
              "value": "community",
              "type": "Text"
            },
            "more_content_button": {
              "__TYPE__": "BooleanContent",
              "value": false
            },
            "more_content_title": {
              "__TYPE__": "FieldContent",
              "value": "fought",
              "type": "Text"
            },
            "more_content_link": {
              "__TYPE__": "LinkContent",
              "value": {
                "__TYPE__": "ExternalLink",
                "url": "http://google.com"
              }
            }
          },
          "items": [
            {
              "__TYPE__": "GroupItemContent",
              "value": []
            }
          ]
        }
      }
    ]
  }
}